{
  "runId": "run-local-20260311-0056",
  "report": [
    {
      "page": "home",
      "viewport": "desktop",
      "before": {
        "width": 1440,
        "height": 9342
      },
      "after": {
        "width": 1440,
        "height": 7444
      },
      "mismatchPixels": 2084275,
      "mismatchPercent": 15.4936
    },
    {
      "page": "home",
      "viewport": "mobile",
      "before": {
        "width": 390,
        "height": 17187
      },
      "after": {
        "width": 390,
        "height": 14973
      },
      "mismatchPixels": 1519726,
      "mismatchPercent": 22.6726
    }
  ]
}